jelinekstat
