Metadata-Version: 1.1
Name: jelinekstat
Version: 0.1.1
Summary: Application software for applying the Second-order tensor statistical proposal of Jelínek (1978).
Home-page: https://github.com/eamontoyaa/jelinekstat
Author: Exneyder A. Montoya-Araque & Ludger O. Suarez-Burgoa
Author-email: eamontoyaa@gmail.com
License: BSD 2-Clause License
Keywords: Anisotropy of Magnetic Susceptibility,Jelínek,tensor,statistics,Python,application software
Platform: UNKNOWN
Classifier: Development Status :: 2 - Pre-Alpha
Classifier: Intended Audience :: Developers
Classifier: License :: OSI Approved :: BSD License
Classifier: Natural Language :: English
Classifier: Programming Language :: Python :: 3.6
